{
  "body_amp": 1.0,
  "arm_amp": 1.0,
  "hand_amp": 1.0,
  "expression_amp": 1.0,
  "target_rig_ghost_opacity": 0.0,
  "target_rig_glow_alpha": 0.42,
  "avatar_joint_node_scale": 1.0,
  "avatar_joint_bone_scale": 1.0,
  "target_mesh_limb_width_scale": 1.0,
  "target_mesh_surface_width_scale": 1.08,
  "target_mesh_rotation_follow": 0.98,
  "target_model_size_scale": 1.22,
  "target_pose_fit_scale": 0.9,
  "retarget_smoothing": 0.45,
  "ik_iterations": 3.0,
  "ik_weight": 0.0,
  "shoulder_correction": 0.0,
  "clavicle_follow": 0.0,
  "elbow_pole_strength": 0.0,
  "knee_pole_strength": 0.0,
  "spine_follow": 0.0,
  "head_follow": 0.0,
  "limb_length_compensation": 0.0,
  "bone_rotation_clamp": 35.0,
  "candidate_id": "baseline",
  "updated_at": "2026-05-24T19:27:35+00:00",
  "best_policy_reward": 32,
  "best_score": 250,
  "source_iter": 0,
  "source_run_id": "browser-pw-rl-20260524-212525",
  "policy_version": 29,
  "policy_publishable": false,
  "policy_learning_only": true
}
