{
  "props": {
    "acquire_editor_element_handle": "<built-in method acquire_editor_element_handle of GLTFExportOptions object at 0x0000014EFB690CF0>",
    "adjust_normalmaps": "True",
    "bake_material_inputs": "<GLTFMaterialBakeMode.USE_MESH_DATA: 2>",
    "call_method": "<built-in method call_method of GLTFExportOptions object at 0x0000014EFB690CF0>",
    "default_input_bake_settings": "{}",
    "default_level_of_detail": "0",
    "default_material_bake_filter": "<TextureFilter.TF_TRILINEAR: 2>",
    "default_material_bake_size": "<Struct 'GLTFMaterialBakeSize' (0x0000014F01B47C00) {x: 1024, y: 1024, auto_detect: True}>",
    "default_material_bake_tiling": "<TextureAddress.TA_WRAP: 0>",
    "export_animation_sequences": "True",
    "export_cameras": "True",
    "export_clear_coat_materials": "True",
    "export_cloth_materials": "True",
    "export_emissive_strength": "True",
    "export_hidden_in_game": "False",
    "export_level_sequences": "True",
    "export_lightmaps": "False",
    "export_lights": "True",
    "export_material_variants": "<GLTFMaterialVariantMode.USE_MESH_DATA: 2>",
    "export_morph_targets": "True",
    "export_preview_mesh": "True",
    "export_proxy_materials": "True",
    "export_source_model": "False",
    "export_specular_glossiness_materials": "True",
    "export_texture_transforms": "True",
    "export_thin_translucent_materials": "False",
    "export_uniform_scale": "0.009999999776482582",
    "export_unlit_materials": "True",
    "export_vertex_colors": "False",
    "export_vertex_skin_weights": "True",
    "get_default_object": "<built-in method get_default_object of type object at 0x0000014EFDD311C8>",
    "get_editor_property": "<built-in method get_editor_property of GLTFExportOptions object at 0x0000014EFB690CF0>",
    "get_full_name": "<built-in method get_full_name of GLTFExportOptions object at 0x0000014EFB690CF0>",
    "get_outermost": "<built-in method get_outermost of GLTFExportOptions object at 0x0000014EFB690CF0>",
    "get_package": "<built-in method get_package of GLTFExportOptions object at 0x0000014EFB690CF0>",
    "get_typed_outer": "<built-in method get_typed_outer of GLTFExportOptions object at 0x0000014EFB690CF0>",
    "get_world": "<built-in method get_world of GLTFExportOptions object at 0x0000014EFB690CF0>",
    "include_copyright_notice": "False",
    "is_editor_property_overridden": "<built-in method is_editor_property_overridden of GLTFExportOptions object at 0x0000014EFB690CF0>",
    "is_package_external": "<built-in method is_package_external of GLTFExportOptions object at 0x0000014EFB690CF0>",
    "make_skinned_meshes_root": "True",
    "modify": "<built-in method modify of GLTFExportOptions object at 0x0000014EFB690CF0>",
    "rename": "<built-in method rename of GLTFExportOptions object at 0x0000014EFB690CF0>",
    "reset_editor_property": "<built-in method reset_editor_property of GLTFExportOptions object at 0x0000014EFB690CF0>",
    "reset_to_default": "<built-in method reset_to_default of GLTFExportOptions object at 0x0000014EFB690CF0>",
    "set_editor_properties": "<built-in method set_editor_properties of GLTFExportOptions object at 0x0000014EFB690CF0>",
    "set_editor_property": "<built-in method set_editor_property of GLTFExportOptions object at 0x0000014EFB690CF0>",
    "skip_near_default_values": "True",
    "static_class": "<built-in method static_class of type object at 0x0000014EFDD311C8>",
    "texture_image_format": "<GLTFTextureImageFormat.PNG: 1>",
    "texture_image_quality": "0",
    "use_importer_material_mapping": "True",
    "use_mesh_quantization": "False"
  },
  "enums": {
    "GLTFMaterialBakeMode": [
      "DISABLED",
      "SIMPLE",
      "USE_MESH_DATA"
    ],
    "GLTFTextureImageFormat": [
      "JPEG",
      "NONE",
      "PNG"
    ],
    "GLTFMaterialPropertyGroup": [
      "AMBIENT_OCCLUSION",
      "BASE_COLOR_OPACITY",
      "CLEAR_COAT_BOTTOM_NORMAL",
      "CLEAR_COAT_ROUGHNESS",
      "EMISSIVE_COLOR",
      "METALLIC_ROUGHNESS",
      "NONE",
      "NORMAL"
    ],
    "GLTFMaterialVariantMode": [
      "NONE",
      "SIMPLE",
      "USE_MESH_DATA"
    ]
  }
}
